transcript_rag/README.md
transcript_rag/__init__.py
transcript_rag/cli.py
transcript_rag/embedding.py
transcript_rag/query.py
transcript_rag-0.1.0.dist-info/METADATA
transcript_rag-0.1.0.dist-info/WHEEL
transcript_rag-0.1.0.dist-info/entry_points.txt
transcript_rag-0.1.0.dist-info/top_level.txt
transcript_rag-0.1.0.dist-info/RECORD
