Metadata-Version: 2.4
Name: transcript-rag
Version: 0.1.0
Summary: Embed transcript files into ChromaDB and query them with RAG
Author: OSCE RAG
Requires-Python: >=3.8
Requires-Dist: chromadb>=0.4
Requires-Dist: sentence-transformers>=2.2.2
Requires-Dist: typer[all]>=0.9
Requires-Dist: langchain>=0.2
Requires-Dist: google-generativeai>=0.1
